<?xml version="1.0" encoding="UTF-8"?>
<vivadoHLSLog:LogRoot xmlns:vivadoHLSLog="www.xilinx.com/vivadoHLSLog">
  <errorLogs>
    <logs>
      <packageLog/>
    </logs>
  </errorLogs>
  <warningLogs>
    <logs>
      <packageLog>
        <logs message="WARNING: [Timing 38-242] The property HD.CLK_SRC of clock port &quot;ap_clk&quot; is not set. In out-of-context mode, this prevents timing estimation for clock delay/skew&#xA;Resolution: Set the HD.CLK_SRC property of the out-of-context port to the location of the clock buffer instance in the top-level design" projectName="copy-max-sharing" solutionName="zcu104" date="2023-01-12T15:34:31.210+0100" type="Warning"/>
        <logs message="WARNING: [Timing 38-242] The property HD.CLK_SRC of clock port &quot;ap_clk&quot; is not set. In out-of-context mode, this prevents timing estimation for clock delay/skew&#xA;Resolution: Set the HD.CLK_SRC property of the out-of-context port to the location of the clock buffer instance in the top-level design" projectName="copy-max-sharing" solutionName="zcu104" date="2023-01-12T15:33:56.553+0100" type="Warning"/>
        <logs message="WARNING: [Route 35-198] Port &quot;counter[27]&quot; does not have an associated HD.PARTPIN_LOCS, which will prevent the partial routing of the signal &quot;counter[27]&quot;. Without this partial route, timing analysis to/from this port will not be accurate, and no routing information for this port can be exported." projectName="copy-max-sharing" solutionName="zcu104" date="2023-01-12T15:33:11.769+0100" type="Warning"/>
        <logs message="WARNING: [Route 35-198] Port &quot;counter[60]&quot; does not have an associated HD.PARTPIN_LOCS, which will prevent the partial routing of the signal &quot;counter[60]&quot;. Without this partial route, timing analysis to/from this port will not be accurate, and no routing information for this port can be exported." projectName="copy-max-sharing" solutionName="zcu104" date="2023-01-12T15:33:11.766+0100" type="Warning"/>
        <logs message="WARNING: [Route 35-198] Port &quot;counter[58]&quot; does not have an associated HD.PARTPIN_LOCS, which will prevent the partial routing of the signal &quot;counter[58]&quot;. Without this partial route, timing analysis to/from this port will not be accurate, and no routing information for this port can be exported." projectName="copy-max-sharing" solutionName="zcu104" date="2023-01-12T15:33:11.763+0100" type="Warning"/>
        <logs message="WARNING: [Route 35-198] Port &quot;counter[28]&quot; does not have an associated HD.PARTPIN_LOCS, which will prevent the partial routing of the signal &quot;counter[28]&quot;. Without this partial route, timing analysis to/from this port will not be accurate, and no routing information for this port can be exported." projectName="copy-max-sharing" solutionName="zcu104" date="2023-01-12T15:33:11.759+0100" type="Warning"/>
        <logs message="WARNING: [Route 35-198] Port &quot;counter[26]&quot; does not have an associated HD.PARTPIN_LOCS, which will prevent the partial routing of the signal &quot;counter[26]&quot;. Without this partial route, timing analysis to/from this port will not be accurate, and no routing information for this port can be exported." projectName="copy-max-sharing" solutionName="zcu104" date="2023-01-12T15:33:11.757+0100" type="Warning"/>
        <logs message="WARNING: [Route 35-198] Port &quot;s_axi_control_wdata[11]&quot; does not have an associated HD.PARTPIN_LOCS, which will prevent the partial routing of the signal &quot;s_axi_control_wdata[11]&quot;. Without this partial route, timing analysis to/from this port will not be accurate, and no routing information for this port can be exported." projectName="copy-max-sharing" solutionName="zcu104" date="2023-01-12T15:33:11.754+0100" type="Warning"/>
        <logs message="WARNING: [Route 35-198] Port &quot;s_axi_control_wdata[10]&quot; does not have an associated HD.PARTPIN_LOCS, which will prevent the partial routing of the signal &quot;s_axi_control_wdata[10]&quot;. Without this partial route, timing analysis to/from this port will not be accurate, and no routing information for this port can be exported." projectName="copy-max-sharing" solutionName="zcu104" date="2023-01-12T15:33:11.750+0100" type="Warning"/>
        <logs message="WARNING: [Route 35-198] Port &quot;s_axi_control_wdata[5]&quot; does not have an associated HD.PARTPIN_LOCS, which will prevent the partial routing of the signal &quot;s_axi_control_wdata[5]&quot;. Without this partial route, timing analysis to/from this port will not be accurate, and no routing information for this port can be exported." projectName="copy-max-sharing" solutionName="zcu104" date="2023-01-12T15:33:11.748+0100" type="Warning"/>
        <logs message="WARNING: [Route 35-198] Port &quot;s_axi_control_wdata[3]&quot; does not have an associated HD.PARTPIN_LOCS, which will prevent the partial routing of the signal &quot;s_axi_control_wdata[3]&quot;. Without this partial route, timing analysis to/from this port will not be accurate, and no routing information for this port can be exported." projectName="copy-max-sharing" solutionName="zcu104" date="2023-01-12T15:33:11.745+0100" type="Warning"/>
        <logs message="WARNING: [Route 35-198] Port &quot;s_axi_control_wdata[17]&quot; does not have an associated HD.PARTPIN_LOCS, which will prevent the partial routing of the signal &quot;s_axi_control_wdata[17]&quot;. Without this partial route, timing analysis to/from this port will not be accurate, and no routing information for this port can be exported." projectName="copy-max-sharing" solutionName="zcu104" date="2023-01-12T15:33:11.742+0100" type="Warning"/>
        <logs message="WARNING: [Route 35-198] Port &quot;s_axi_control_wdata[16]&quot; does not have an associated HD.PARTPIN_LOCS, which will prevent the partial routing of the signal &quot;s_axi_control_wdata[16]&quot;. Without this partial route, timing analysis to/from this port will not be accurate, and no routing information for this port can be exported." projectName="copy-max-sharing" solutionName="zcu104" date="2023-01-12T15:33:11.739+0100" type="Warning"/>
        <logs message="WARNING: [Route 35-198] Port &quot;s_axi_control_wstrb[2]&quot; does not have an associated HD.PARTPIN_LOCS, which will prevent the partial routing of the signal &quot;s_axi_control_wstrb[2]&quot;. Without this partial route, timing analysis to/from this port will not be accurate, and no routing information for this port can be exported." projectName="copy-max-sharing" solutionName="zcu104" date="2023-01-12T15:33:11.736+0100" type="Warning"/>
        <logs message="WARNING: [Route 35-198] Port &quot;s_axi_control_wdata[9]&quot; does not have an associated HD.PARTPIN_LOCS, which will prevent the partial routing of the signal &quot;s_axi_control_wdata[9]&quot;. Without this partial route, timing analysis to/from this port will not be accurate, and no routing information for this port can be exported." projectName="copy-max-sharing" solutionName="zcu104" date="2023-01-12T15:33:11.734+0100" type="Warning"/>
        <logs message="WARNING: [Route 35-198] Port &quot;s_axi_control_wdata[8]&quot; does not have an associated HD.PARTPIN_LOCS, which will prevent the partial routing of the signal &quot;s_axi_control_wdata[8]&quot;. Without this partial route, timing analysis to/from this port will not be accurate, and no routing information for this port can be exported." projectName="copy-max-sharing" solutionName="zcu104" date="2023-01-12T15:33:11.731+0100" type="Warning"/>
        <logs message="WARNING: [Route 35-198] Port &quot;s_axi_control_wstrb[1]&quot; does not have an associated HD.PARTPIN_LOCS, which will prevent the partial routing of the signal &quot;s_axi_control_wstrb[1]&quot;. Without this partial route, timing analysis to/from this port will not be accurate, and no routing information for this port can be exported." projectName="copy-max-sharing" solutionName="zcu104" date="2023-01-12T15:33:11.729+0100" type="Warning"/>
        <logs message="WARNING: [Route 35-198] Port &quot;s_axi_control_wdata[7]&quot; does not have an associated HD.PARTPIN_LOCS, which will prevent the partial routing of the signal &quot;s_axi_control_wdata[7]&quot;. Without this partial route, timing analysis to/from this port will not be accurate, and no routing information for this port can be exported." projectName="copy-max-sharing" solutionName="zcu104" date="2023-01-12T15:33:11.726+0100" type="Warning"/>
        <logs message="WARNING: [Route 35-198] Port &quot;s_axi_control_wdata[6]&quot; does not have an associated HD.PARTPIN_LOCS, which will prevent the partial routing of the signal &quot;s_axi_control_wdata[6]&quot;. Without this partial route, timing analysis to/from this port will not be accurate, and no routing information for this port can be exported." projectName="copy-max-sharing" solutionName="zcu104" date="2023-01-12T15:33:11.723+0100" type="Warning"/>
        <logs message="WARNING: [Route 35-198] Port &quot;s_axi_control_wstrb[0]&quot; does not have an associated HD.PARTPIN_LOCS, which will prevent the partial routing of the signal &quot;s_axi_control_wstrb[0]&quot;. Without this partial route, timing analysis to/from this port will not be accurate, and no routing information for this port can be exported." projectName="copy-max-sharing" solutionName="zcu104" date="2023-01-12T15:33:11.720+0100" type="Warning"/>
        <logs message="WARNING: [Route 35-198] Port &quot;counter[39]&quot; does not have an associated HD.PARTPIN_LOCS, which will prevent the partial routing of the signal &quot;counter[39]&quot;. Without this partial route, timing analysis to/from this port will not be accurate, and no routing information for this port can be exported." projectName="copy-max-sharing" solutionName="zcu104" date="2023-01-12T15:33:11.718+0100" type="Warning"/>
        <logs message="WARNING: [Route 35-198] Port &quot;s_axi_control_araddr[2]&quot; does not have an associated HD.PARTPIN_LOCS, which will prevent the partial routing of the signal &quot;s_axi_control_araddr[2]&quot;. Without this partial route, timing analysis to/from this port will not be accurate, and no routing information for this port can be exported." projectName="copy-max-sharing" solutionName="zcu104" date="2023-01-12T15:33:11.715+0100" type="Warning"/>
        <logs message="WARNING: [Route 35-198] Port &quot;s_axi_control_araddr[3]&quot; does not have an associated HD.PARTPIN_LOCS, which will prevent the partial routing of the signal &quot;s_axi_control_araddr[3]&quot;. Without this partial route, timing analysis to/from this port will not be accurate, and no routing information for this port can be exported." projectName="copy-max-sharing" solutionName="zcu104" date="2023-01-12T15:33:11.713+0100" type="Warning"/>
        <logs message="WARNING: [Route 35-198] Port &quot;s_axi_control_araddr[4]&quot; does not have an associated HD.PARTPIN_LOCS, which will prevent the partial routing of the signal &quot;s_axi_control_araddr[4]&quot;. Without this partial route, timing analysis to/from this port will not be accurate, and no routing information for this port can be exported." projectName="copy-max-sharing" solutionName="zcu104" date="2023-01-12T15:33:11.710+0100" type="Warning"/>
        <logs message="WARNING: [Route 35-198] Port &quot;s_axi_control_araddr[5]&quot; does not have an associated HD.PARTPIN_LOCS, which will prevent the partial routing of the signal &quot;s_axi_control_araddr[5]&quot;. Without this partial route, timing analysis to/from this port will not be accurate, and no routing information for this port can be exported." projectName="copy-max-sharing" solutionName="zcu104" date="2023-01-12T15:33:11.708+0100" type="Warning"/>
        <logs message="WARNING: [Route 35-198] Port &quot;s_axi_control_wdata[1]&quot; does not have an associated HD.PARTPIN_LOCS, which will prevent the partial routing of the signal &quot;s_axi_control_wdata[1]&quot;. Without this partial route, timing analysis to/from this port will not be accurate, and no routing information for this port can be exported." projectName="copy-max-sharing" solutionName="zcu104" date="2023-01-12T15:33:11.706+0100" type="Warning"/>
        <logs message="WARNING: [Route 35-198] Port &quot;counter[33]&quot; does not have an associated HD.PARTPIN_LOCS, which will prevent the partial routing of the signal &quot;counter[33]&quot;. Without this partial route, timing analysis to/from this port will not be accurate, and no routing information for this port can be exported." projectName="copy-max-sharing" solutionName="zcu104" date="2023-01-12T15:33:11.704+0100" type="Warning"/>
        <logs message="WARNING: [Route 35-198] Port &quot;counter[1]&quot; does not have an associated HD.PARTPIN_LOCS, which will prevent the partial routing of the signal &quot;counter[1]&quot;. Without this partial route, timing analysis to/from this port will not be accurate, and no routing information for this port can be exported." projectName="copy-max-sharing" solutionName="zcu104" date="2023-01-12T15:33:11.701+0100" type="Warning"/>
        <logs message="WARNING: [Route 35-198] Port &quot;counter[7]&quot; does not have an associated HD.PARTPIN_LOCS, which will prevent the partial routing of the signal &quot;counter[7]&quot;. Without this partial route, timing analysis to/from this port will not be accurate, and no routing information for this port can be exported." projectName="copy-max-sharing" solutionName="zcu104" date="2023-01-12T15:33:11.699+0100" type="Warning"/>
        <logs message="WARNING: [Route 35-198] Port &quot;counter[32]&quot; does not have an associated HD.PARTPIN_LOCS, which will prevent the partial routing of the signal &quot;counter[32]&quot;. Without this partial route, timing analysis to/from this port will not be accurate, and no routing information for this port can be exported." projectName="copy-max-sharing" solutionName="zcu104" date="2023-01-12T15:33:11.696+0100" type="Warning"/>
        <logs message="WARNING: [Route 35-198] Port &quot;counter[0]&quot; does not have an associated HD.PARTPIN_LOCS, which will prevent the partial routing of the signal &quot;counter[0]&quot;. Without this partial route, timing analysis to/from this port will not be accurate, and no routing information for this port can be exported." projectName="copy-max-sharing" solutionName="zcu104" date="2023-01-12T15:33:11.694+0100" type="Warning"/>
        <logs message="WARNING: [Route 35-198] Port &quot;m_axi_data_arready&quot; does not have an associated HD.PARTPIN_LOCS, which will prevent the partial routing of the signal &quot;m_axi_data_arready&quot;. Without this partial route, timing analysis to/from this port will not be accurate, and no routing information for this port can be exported." projectName="copy-max-sharing" solutionName="zcu104" date="2023-01-12T15:33:11.692+0100" type="Warning"/>
        <logs message="WARNING: [Route 35-198] Port &quot;m_axi_data_bvalid&quot; does not have an associated HD.PARTPIN_LOCS, which will prevent the partial routing of the signal &quot;m_axi_data_bvalid&quot;. Without this partial route, timing analysis to/from this port will not be accurate, and no routing information for this port can be exported." projectName="copy-max-sharing" solutionName="zcu104" date="2023-01-12T15:33:11.690+0100" type="Warning"/>
        <logs message="WARNING: [Route 35-198] Port &quot;m_axi_data_rvalid&quot; does not have an associated HD.PARTPIN_LOCS, which will prevent the partial routing of the signal &quot;m_axi_data_rvalid&quot;. Without this partial route, timing analysis to/from this port will not be accurate, and no routing information for this port can be exported." projectName="copy-max-sharing" solutionName="zcu104" date="2023-01-12T15:33:11.688+0100" type="Warning"/>
        <logs message="WARNING: [Route 35-198] Port &quot;m_axi_data_rlast&quot; does not have an associated HD.PARTPIN_LOCS, which will prevent the partial routing of the signal &quot;m_axi_data_rlast&quot;. Without this partial route, timing analysis to/from this port will not be accurate, and no routing information for this port can be exported." projectName="copy-max-sharing" solutionName="zcu104" date="2023-01-12T15:33:11.686+0100" type="Warning"/>
        <logs message="WARNING: [Route 35-198] Port &quot;m_axi_data_rdata[59]&quot; does not have an associated HD.PARTPIN_LOCS, which will prevent the partial routing of the signal &quot;m_axi_data_rdata[59]&quot;. Without this partial route, timing analysis to/from this port will not be accurate, and no routing information for this port can be exported." projectName="copy-max-sharing" solutionName="zcu104" date="2023-01-12T15:33:11.683+0100" type="Warning"/>
        <logs message="WARNING: [Route 35-198] Port &quot;m_axi_data_rdata[45]&quot; does not have an associated HD.PARTPIN_LOCS, which will prevent the partial routing of the signal &quot;m_axi_data_rdata[45]&quot;. Without this partial route, timing analysis to/from this port will not be accurate, and no routing information for this port can be exported." projectName="copy-max-sharing" solutionName="zcu104" date="2023-01-12T15:33:11.682+0100" type="Warning"/>
        <logs message="WARNING: [Route 35-198] Port &quot;m_axi_data_rdata[15]&quot; does not have an associated HD.PARTPIN_LOCS, which will prevent the partial routing of the signal &quot;m_axi_data_rdata[15]&quot;. Without this partial route, timing analysis to/from this port will not be accurate, and no routing information for this port can be exported." projectName="copy-max-sharing" solutionName="zcu104" date="2023-01-12T15:33:11.680+0100" type="Warning"/>
        <logs message="WARNING: [Route 35-198] Port &quot;m_axi_data_rdata[5]&quot; does not have an associated HD.PARTPIN_LOCS, which will prevent the partial routing of the signal &quot;m_axi_data_rdata[5]&quot;. Without this partial route, timing analysis to/from this port will not be accurate, and no routing information for this port can be exported." projectName="copy-max-sharing" solutionName="zcu104" date="2023-01-12T15:33:11.677+0100" type="Warning"/>
        <logs message="WARNING: [Route 35-198] Port &quot;m_axi_data_rdata[57]&quot; does not have an associated HD.PARTPIN_LOCS, which will prevent the partial routing of the signal &quot;m_axi_data_rdata[57]&quot;. Without this partial route, timing analysis to/from this port will not be accurate, and no routing information for this port can be exported." projectName="copy-max-sharing" solutionName="zcu104" date="2023-01-12T15:33:11.676+0100" type="Warning"/>
        <logs message="WARNING: [Route 35-198] Port &quot;m_axi_data_rdata[55]&quot; does not have an associated HD.PARTPIN_LOCS, which will prevent the partial routing of the signal &quot;m_axi_data_rdata[55]&quot;. Without this partial route, timing analysis to/from this port will not be accurate, and no routing information for this port can be exported." projectName="copy-max-sharing" solutionName="zcu104" date="2023-01-12T15:33:11.674+0100" type="Warning"/>
        <logs message="WARNING: [Route 35-198] Port &quot;m_axi_data_rdata[51]&quot; does not have an associated HD.PARTPIN_LOCS, which will prevent the partial routing of the signal &quot;m_axi_data_rdata[51]&quot;. Without this partial route, timing analysis to/from this port will not be accurate, and no routing information for this port can be exported." projectName="copy-max-sharing" solutionName="zcu104" date="2023-01-12T15:33:11.671+0100" type="Warning"/>
        <logs message="WARNING: [Route 35-198] Port &quot;m_axi_data_rdata[43]&quot; does not have an associated HD.PARTPIN_LOCS, which will prevent the partial routing of the signal &quot;m_axi_data_rdata[43]&quot;. Without this partial route, timing analysis to/from this port will not be accurate, and no routing information for this port can be exported." projectName="copy-max-sharing" solutionName="zcu104" date="2023-01-12T15:33:11.669+0100" type="Warning"/>
        <logs message="WARNING: [Route 35-198] Port &quot;m_axi_data_rdata[37]&quot; does not have an associated HD.PARTPIN_LOCS, which will prevent the partial routing of the signal &quot;m_axi_data_rdata[37]&quot;. Without this partial route, timing analysis to/from this port will not be accurate, and no routing information for this port can be exported." projectName="copy-max-sharing" solutionName="zcu104" date="2023-01-12T15:33:11.667+0100" type="Warning"/>
      </packageLog>
    </logs>
  </warningLogs>
</vivadoHLSLog:LogRoot>
